{"display": "Timing Components >> Mechanical (Specifications)", "title": "Mechanical", "content": "<b>VALVE TIMING :</b><br/>\n&nbsp;Valve Overlap  ....................   66.0&deg;<br/>\n<br/>\n&nbsp;<b>Exhaust Valve:</b> <br/>\n&nbsp;&nbsp;&nbsp;&nbsp;Closes (ATC)  ....................   42.5&deg;<br/>\n&nbsp;&nbsp;&nbsp;&nbsp;Opens (BBC)  ....................   82.5&deg;<br/>\n&nbsp;&nbsp;&nbsp;&nbsp;Duration  ....................   305.0&deg;<br/>\n<br/>\n&nbsp;<b>Intake Valve:</b><br/>\n&nbsp;&nbsp;&nbsp;&nbsp;Closes (BTDC)  ....................   86.5&deg;<br/>\n&nbsp;&nbsp;&nbsp;&nbsp;Opens  ....................   23.5&deg;<br/>\n&nbsp;&nbsp;&nbsp;&nbsp;Duration  ....................   297.0&deg;<br/>\n<br/>\n<br/>\n<br/>\n<br/>\n<br/>\n", "image": null, "fname": "21136/specs/TimingComponents__MechanicalSpecifications.json"}